ometa/__init__.py
ometa/boot.py
ometa/builder.py
ometa/grammar.py
ometa/runtime.py
ometa/test/__init__.py
ometa/test/test_builder.py
ometa/test/test_ometa.py
ometa/test/test_runtime.py
python_ometa-0.0.1.dist-info/LICENSE
python_ometa-0.0.1.dist-info/METADATA
python_ometa-0.0.1.dist-info/WHEEL
python_ometa-0.0.1.dist-info/top_level.txt
python_ometa-0.0.1.dist-info/RECORD
